<detections><detection x_min="993" y_min="938" x_max="2856" y_max="2078" confidence="0.9512084" class_id="3" /><detection x_min="281" y_min="1965" x_max="925" y_max="2666" confidence="0.9505859" class_id="2" /><detection x_min="2993" y_min="876" x_max="3837" y_max="1614" confidence="0.9439391" class_id="2" /><detection x_min="3012" y_min="1765" x_max="3837" y_max="2341" confidence="0.9210914" class_id="2" /><detection x_min="350" y_min="951" x_max="968" y_max="1808" confidence="0.90680903" class_id="2" /><detection x_min="750" y_min="550" x_max="2475" y_max="920" confidence="0.88703775" class_id="1" /><detection x_min="3012" y_min="1652" x_max="3831" y_max="1752" confidence="0.8772213" class_id="1" /><detection x_min="337" y_min="1834" x_max="950" y_max="1934" confidence="0.8548439" class_id="1" /><detection x_min="343" y_min="262" x_max="3818" y_max="463" confidence="0.8231014" class_id="0" /><detection x_min="962" y_min="2197" x_max="1506" y_max="2672" confidence="0.8123355" class_id="2" /><detection x_min="1531" y_min="2090" x_max="2887" y_max="2660" confidence="0.8002106" class_id="3" /><detection x_min="3043" y_min="2478" x_max="3806" y_max="2641" confidence="0.793331" class_id="2" /><detection x_min="2993" y_min="507" x_max="3812" y_max="845" confidence="0.75665474" class_id="1" /><detection x_min="3056" y_min="2372" x_max="3812" y_max="2459" confidence="0.70653105" class_id="1" /></detections>